opda/__init__.py
opda/_approximations.json
opda/approximation.py
opda/exceptions.py
opda/nonparametric.py
opda/parametric.py
opda/random.py
opda/utils.py
opda-0.8.0.dist-info/licenses/LICENSE
opda-0.8.0.dist-info/METADATA
opda-0.8.0.dist-info/WHEEL
opda-0.8.0.dist-info/top_level.txt
opda-0.8.0.dist-info/RECORD
