Metadata-Version: 2.4
Name: opda
Version: 0.8.0
Summary: Design and analyze optimal deep learning models.
Author-email: Nicholas Lourie <dev@nicholaslourie.com>
License-Expression: Apache-2.0
Project-URL: Documentation, https://nicholaslourie.github.io/opda
Project-URL: Source, https://github.com/nicholaslourie/opda
Project-URL: Issues, https://github.com/nicholaslourie/opda/issues
Project-URL: Changelog, https://nicholaslourie.github.io/opda/changelog.html
Keywords: opda,optimal design analysis,hyperparameter tuning,machine learning,ml,deep learning,dl,artificial intelligence,ai
Classifier: Development Status :: 4 - Beta
Classifier: Intended Audience :: Science/Research
Classifier: Natural Language :: English
Classifier: Programming Language :: Python
Classifier: Programming Language :: Python :: 3
Classifier: Programming Language :: Python :: 3.9
Classifier: Programming Language :: Python :: 3.10
Classifier: Programming Language :: Python :: 3.11
Classifier: Programming Language :: Python :: 3.12
Classifier: Programming Language :: Python :: 3.13
Classifier: Operating System :: OS Independent
Classifier: Topic :: Scientific/Engineering
Classifier: Topic :: Scientific/Engineering :: Artificial Intelligence
Requires-Python: >=3.9
License-File: LICENSE
Requires-Dist: numpy>=1.26
Requires-Dist: scipy>=1.11
Provides-Extra: nbs
Requires-Dist: notebook==7.0.6; extra == "nbs"
Provides-Extra: lint
Requires-Dist: ruff==0.1.13; extra == "lint"
Provides-Extra: docs
Requires-Dist: furo==2023.9.10; extra == "docs"
Requires-Dist: matplotlib==3.7.4; extra == "docs"
Requires-Dist: numpydoc==1.6.0; extra == "docs"
Requires-Dist: sphinx==7.1.2; extra == "docs"
Requires-Dist: tomli; python_version < "3.11" and extra == "docs"
Provides-Extra: test
Requires-Dist: pytest==7.4.4; extra == "test"
Provides-Extra: package
Requires-Dist: build==1.2.2; extra == "package"
Requires-Dist: twine==6.1.0; extra == "package"
Provides-Extra: ci
Requires-Dist: lxml==5.3.0; extra == "ci"
Requires-Dist: nox==2023.4.22; extra == "ci"
Requires-Dist: requests==2.31.0; extra == "ci"
Requires-Dist: tomli; python_version < "3.11" and extra == "ci"
Dynamic: license-file
